pillars/__init__.py
pillars/app.py
pillars/base.py
pillars/engines/__init__.py
pillars/engines/ari.py
pillars/engines/pg.py
pillars/engines/redis.py
pillars/engines/systemd.py
pillars/exceptions.py
pillars/middlewares/__init__.py
pillars/middlewares/http.py
pillars/middlewares/pg.py
pillars/py.typed
pillars/request.py
pillars/sites/__init__.py
pillars/sites/datagram.py
pillars/sites/protocol.py
pillars/sites/websocket.py
pillars/transports/__init__.py
pillars/transports/ari.py
pillars/transports/fast_agi.py
pillars/transports/http.py
pillars/transports/sip.py
pillars/transports/syslog.py
pillars/utils.py
pillars-0.4.1.dist-info/WHEEL
pillars-0.4.1.dist-info/METADATA
pillars-0.4.1.dist-info/RECORD
